README.md
click_stream.py
setup.py
click_stream.egg-info/PKG-INFO
click_stream.egg-info/SOURCES.txt
click_stream.egg-info/dependency_links.txt
click_stream.egg-info/top_level.txt