Metadata-Version: 1.0
Name: click-stream
Version: 0.0.9
Summary: Click option type for http/https/file inputs
Home-page: https://github.com/Moshe/click-stream
Author: Moshe Zada
Author-email: UNKNOWN
License: UNKNOWN
Keywords: click,stream,cli,url
Platform: UNKNOWN
